{
  "id": "op:GET:/rest/v2.0/companies/{company_id}/budget_views/{budget_view_id}/project_status_snapshots",
  "method": "GET",
  "path_template": "/rest/v2.0/companies/{company_id}/budget_views/{budget_view_id}/project_status_snapshots",
  "declared": {
    "parameters": [
      {
        "name": "filters[approval_status]",
        "location": "query",
        "required": false,
        "schema_id": "schema:anon/dd14b24ce32314f1bbc082942a125f34821ed7fb",
        "description": "Filter by approval status",
        "deprecated": null,
        "explode": null,
        "style": null,
        "provenance": {
          "source_file": "/Users/taylorhale/Documents/dev_hub/Brynhild/repos/Schmith/spec/procore/api.json",
          "source_pointer": "#/paths//rest/v2.0/companies/{company_id}/budget_views/{budget_view_id}/project_status_snapshots/get/parameters",
          "via": []
        },
        "availability": {
          "name": "native",
          "location": "native",
          "required": "native",
          "schema_id": "adapter",
          "description": "native",
          "deprecated": "absent",
          "explode": "absent",
          "style": "absent",
          "provenance": "native"
        }
      },
      {
        "name": "filters[status_id]",
        "location": "query",
        "required": false,
        "schema_id": "schema:anon/5b1cd5713a375e18bb93e9635b8a2dc5fc2672cf",
        "description": "Filter snapshots by PSS custom status ID",
        "deprecated": null,
        "explode": null,
        "style": null,
        "provenance": {
          "source_file": "/Users/taylorhale/Documents/dev_hub/Brynhild/repos/Schmith/spec/procore/api.json",
          "source_pointer": "#/paths//rest/v2.0/companies/{company_id}/budget_views/{budget_view_id}/project_status_snapshots/get/parameters",
          "via": []
        },
        "availability": {
          "name": "native",
          "location": "native",
          "required": "native",
          "schema_id": "adapter",
          "description": "native",
          "deprecated": "absent",
          "explode": "absent",
          "style": "absent",
          "provenance": "native"
        }
      },
      {
        "name": "filters[project_id]",
        "location": "query",
        "required": false,
        "schema_id": "schema:anon/5b1cd5713a375e18bb93e9635b8a2dc5fc2672cf",
        "description": "Filter snapshots by project ID",
        "deprecated": null,
        "explode": null,
        "style": null,
        "provenance": {
          "source_file": "/Users/taylorhale/Documents/dev_hub/Brynhild/repos/Schmith/spec/procore/api.json",
          "source_pointer": "#/paths//rest/v2.0/companies/{company_id}/budget_views/{budget_view_id}/project_status_snapshots/get/parameters",
          "via": []
        },
        "availability": {
          "name": "native",
          "location": "native",
          "required": "native",
          "schema_id": "adapter",
          "description": "native",
          "deprecated": "absent",
          "explode": "absent",
          "style": "absent",
          "provenance": "native"
        }
      },
      {
        "name": "filters[region_id]",
        "location": "query",
        "required": false,
        "schema_id": "schema:anon/5b1cd5713a375e18bb93e9635b8a2dc5fc2672cf",
        "description": "Filter snapshots by region ID",
        "deprecated": null,
        "explode": null,
        "style": null,
        "provenance": {
          "source_file": "/Users/taylorhale/Documents/dev_hub/Brynhild/repos/Schmith/spec/procore/api.json",
          "source_pointer": "#/paths//rest/v2.0/companies/{company_id}/budget_views/{budget_view_id}/project_status_snapshots/get/parameters",
          "via": []
        },
        "availability": {
          "name": "native",
          "location": "native",
          "required": "native",
          "schema_id": "adapter",
          "description": "native",
          "deprecated": "absent",
          "explode": "absent",
          "style": "absent",
          "provenance": "native"
        }
      },
      {
        "name": "filters[stage_id]",
        "location": "query",
        "required": false,
        "schema_id": "schema:anon/5b1cd5713a375e18bb93e9635b8a2dc5fc2672cf",
        "description": "Filter snapshots by stage ID",
        "deprecated": null,
        "explode": null,
        "style": null,
        "provenance": {
          "source_file": "/Users/taylorhale/Documents/dev_hub/Brynhild/repos/Schmith/spec/procore/api.json",
          "source_pointer": "#/paths//rest/v2.0/companies/{company_id}/budget_views/{budget_view_id}/project_status_snapshots/get/parameters",
          "via": []
        },
        "availability": {
          "name": "native",
          "location": "native",
          "required": "native",
          "schema_id": "adapter",
          "description": "native",
          "deprecated": "absent",
          "explode": "absent",
          "style": "absent",
          "provenance": "native"
        }
      },
      {
        "name": "filters[office_id]",
        "location": "query",
        "required": false,
        "schema_id": "schema:anon/5b1cd5713a375e18bb93e9635b8a2dc5fc2672cf",
        "description": "Filter snapshots by office ID",
        "deprecated": null,
        "explode": null,
        "style": null,
        "provenance": {
          "source_file": "/Users/taylorhale/Documents/dev_hub/Brynhild/repos/Schmith/spec/procore/api.json",
          "source_pointer": "#/paths//rest/v2.0/companies/{company_id}/budget_views/{budget_view_id}/project_status_snapshots/get/parameters",
          "via": []
        },
        "availability": {
          "name": "native",
          "location": "native",
          "required": "native",
          "schema_id": "adapter",
          "description": "native",
          "deprecated": "absent",
          "explode": "absent",
          "style": "absent",
          "provenance": "native"
        }
      },
      {
        "name": "filters[created_by_id]",
        "location": "query",
        "required": false,
        "schema_id": "schema:anon/5b1cd5713a375e18bb93e9635b8a2dc5fc2672cf",
        "description": "Filter snapshots by created_by_id",
        "deprecated": null,
        "explode": null,
        "style": null,
        "provenance": {
          "source_file": "/Users/taylorhale/Documents/dev_hub/Brynhild/repos/Schmith/spec/procore/api.json",
          "source_pointer": "#/paths//rest/v2.0/companies/{company_id}/budget_views/{budget_view_id}/project_status_snapshots/get/parameters",
          "via": []
        },
        "availability": {
          "name": "native",
          "location": "native",
          "required": "native",
          "schema_id": "adapter",
          "description": "native",
          "deprecated": "absent",
          "explode": "absent",
          "style": "absent",
          "provenance": "native"
        }
      },
      {
        "name": "filters[created_at]",
        "location": "query",
        "required": false,
        "schema_id": "schema:anon/896926c1f43693d85bb57bbd5c316c6c06b025b8",
        "description": "Filter snapshots by created_at date range, inclusive",
        "deprecated": null,
        "explode": null,
        "style": null,
        "provenance": {
          "source_file": "/Users/taylorhale/Documents/dev_hub/Brynhild/repos/Schmith/spec/procore/api.json",
          "source_pointer": "#/paths//rest/v2.0/companies/{company_id}/budget_views/{budget_view_id}/project_status_snapshots/get/parameters",
          "via": []
        },
        "availability": {
          "name": "native",
          "location": "native",
          "required": "native",
          "schema_id": "adapter",
          "description": "native",
          "deprecated": "absent",
          "explode": "absent",
          "style": "absent",
          "provenance": "native"
        }
      },
      {
        "name": "sort",
        "location": "query",
        "required": false,
        "schema_id": "schema:anon/cfafced046e509146c9abefe0824cf3dc9beb349",
        "description": "Sort parameter",
        "deprecated": null,
        "explode": null,
        "style": null,
        "provenance": {
          "source_file": "/Users/taylorhale/Documents/dev_hub/Brynhild/repos/Schmith/spec/procore/api.json",
          "source_pointer": "#/paths//rest/v2.0/companies/{company_id}/budget_views/{budget_view_id}/project_status_snapshots/get/parameters",
          "via": []
        },
        "availability": {
          "name": "native",
          "location": "native",
          "required": "native",
          "schema_id": "adapter",
          "description": "native",
          "deprecated": "absent",
          "explode": "absent",
          "style": "absent",
          "provenance": "native"
        }
      },
      {
        "name": "page",
        "location": "query",
        "required": false,
        "schema_id": "schema:anon/4df23f6fcb2f843ba1603f8fd67bfbb0659b678d",
        "description": "Page",
        "deprecated": null,
        "explode": null,
        "style": null,
        "provenance": {
          "source_file": "/Users/taylorhale/Documents/dev_hub/Brynhild/repos/Schmith/spec/procore/api.json",
          "source_pointer": "#/paths//rest/v2.0/companies/{company_id}/budget_views/{budget_view_id}/project_status_snapshots/get/parameters",
          "via": []
        },
        "availability": {
          "name": "native",
          "location": "native",
          "required": "native",
          "schema_id": "adapter",
          "description": "native",
          "deprecated": "absent",
          "explode": "absent",
          "style": "absent",
          "provenance": "native"
        }
      },
      {
        "name": "per_page",
        "location": "query",
        "required": false,
        "schema_id": "schema:anon/88ee9d4fe668231f605731a691290c81b2c96179",
        "description": "Elements per page",
        "deprecated": null,
        "explode": null,
        "style": null,
        "provenance": {
          "source_file": "/Users/taylorhale/Documents/dev_hub/Brynhild/repos/Schmith/spec/procore/api.json",
          "source_pointer": "#/paths//rest/v2.0/companies/{company_id}/budget_views/{budget_view_id}/project_status_snapshots/get/parameters",
          "via": []
        },
        "availability": {
          "name": "native",
          "location": "native",
          "required": "native",
          "schema_id": "adapter",
          "description": "native",
          "deprecated": "absent",
          "explode": "absent",
          "style": "absent",
          "provenance": "native"
        }
      },
      {
        "name": "Procore-Company-Id",
        "location": "header",
        "required": true,
        "schema_id": "schema:anon/4df23f6fcb2f843ba1603f8fd67bfbb0659b678d",
        "description": "Unique company identifier associated with the Procore User Account.",
        "deprecated": null,
        "explode": null,
        "style": null,
        "provenance": {
          "source_file": "/Users/taylorhale/Documents/dev_hub/Brynhild/repos/Schmith/spec/procore/api.json",
          "source_pointer": "#/paths//rest/v2.0/companies/{company_id}/budget_views/{budget_view_id}/project_status_snapshots/get/parameters",
          "via": []
        },
        "availability": {
          "name": "native",
          "location": "native",
          "required": "native",
          "schema_id": "adapter",
          "description": "native",
          "deprecated": "absent",
          "explode": "absent",
          "style": "absent",
          "provenance": "native"
        }
      },
      {
        "name": "company_id",
        "location": "path",
        "required": true,
        "schema_id": "schema:anon/5b1cd5713a375e18bb93e9635b8a2dc5fc2672cf",
        "description": "Unique identifier for the company.",
        "deprecated": null,
        "explode": null,
        "style": null,
        "provenance": {
          "source_file": "/Users/taylorhale/Documents/dev_hub/Brynhild/repos/Schmith/spec/procore/api.json",
          "source_pointer": "#/paths//rest/v2.0/companies/{company_id}/budget_views/{budget_view_id}/project_status_snapshots/get/parameters",
          "via": []
        },
        "availability": {
          "name": "native",
          "location": "native",
          "required": "native",
          "schema_id": "adapter",
          "description": "native",
          "deprecated": "absent",
          "explode": "absent",
          "style": "absent",
          "provenance": "native"
        }
      },
      {
        "name": "budget_view_id",
        "location": "path",
        "required": true,
        "schema_id": "schema:anon/5b1cd5713a375e18bb93e9635b8a2dc5fc2672cf",
        "description": "ID of the budget view",
        "deprecated": null,
        "explode": null,
        "style": null,
        "provenance": {
          "source_file": "/Users/taylorhale/Documents/dev_hub/Brynhild/repos/Schmith/spec/procore/api.json",
          "source_pointer": "#/paths//rest/v2.0/companies/{company_id}/budget_views/{budget_view_id}/project_status_snapshots/get/parameters",
          "via": []
        },
        "availability": {
          "name": "native",
          "location": "native",
          "required": "native",
          "schema_id": "adapter",
          "description": "native",
          "deprecated": "absent",
          "explode": "absent",
          "style": "absent",
          "provenance": "native"
        }
      }
    ],
    "request_bodies": [],
    "responses": [
      {
        "status_code": "200",
        "media_type": "application/json",
        "schema_id": "schema:anon/acd798d584ee5ff3e54e26fc31fb105ca48c0a49",
        "description": "OK",
        "provenance": {
          "source_file": "/Users/taylorhale/Documents/dev_hub/Brynhild/repos/Schmith/spec/procore/api.json",
          "source_pointer": "#/paths//rest/v2.0/companies/{company_id}/budget_views/{budget_view_id}/project_status_snapshots/get/responses/200",
          "via": []
        },
        "availability": {
          "status_code": "native",
          "media_type": "native",
          "schema_id": "adapter",
          "description": "native",
          "provenance": "native"
        }
      },
      {
        "status_code": "400",
        "media_type": "application/json",
        "schema_id": "schema:anon/3ff1c5fdb9b08c6e4d5f4bea9bae42c60eb39a1a",
        "description": "Bad Request",
        "provenance": {
          "source_file": "/Users/taylorhale/Documents/dev_hub/Brynhild/repos/Schmith/spec/procore/api.json",
          "source_pointer": "#/paths//rest/v2.0/companies/{company_id}/budget_views/{budget_view_id}/project_status_snapshots/get/responses/400",
          "via": []
        },
        "availability": {
          "status_code": "native",
          "media_type": "native",
          "schema_id": "adapter",
          "description": "native",
          "provenance": "native"
        }
      },
      {
        "status_code": "401",
        "media_type": "application/json",
        "schema_id": "schema:anon/3ff1c5fdb9b08c6e4d5f4bea9bae42c60eb39a1a",
        "description": "Unauthorized",
        "provenance": {
          "source_file": "/Users/taylorhale/Documents/dev_hub/Brynhild/repos/Schmith/spec/procore/api.json",
          "source_pointer": "#/paths//rest/v2.0/companies/{company_id}/budget_views/{budget_view_id}/project_status_snapshots/get/responses/401",
          "via": []
        },
        "availability": {
          "status_code": "native",
          "media_type": "native",
          "schema_id": "adapter",
          "description": "native",
          "provenance": "native"
        }
      },
      {
        "status_code": "403",
        "media_type": "application/json",
        "schema_id": "schema:anon/3ff1c5fdb9b08c6e4d5f4bea9bae42c60eb39a1a",
        "description": "Forbidden",
        "provenance": {
          "source_file": "/Users/taylorhale/Documents/dev_hub/Brynhild/repos/Schmith/spec/procore/api.json",
          "source_pointer": "#/paths//rest/v2.0/companies/{company_id}/budget_views/{budget_view_id}/project_status_snapshots/get/responses/403",
          "via": []
        },
        "availability": {
          "status_code": "native",
          "media_type": "native",
          "schema_id": "adapter",
          "description": "native",
          "provenance": "native"
        }
      },
      {
        "status_code": "422",
        "media_type": "application/json",
        "schema_id": "schema:anon/3ff1c5fdb9b08c6e4d5f4bea9bae42c60eb39a1a",
        "description": "Unprocessable Entity",
        "provenance": {
          "source_file": "/Users/taylorhale/Documents/dev_hub/Brynhild/repos/Schmith/spec/procore/api.json",
          "source_pointer": "#/paths//rest/v2.0/companies/{company_id}/budget_views/{budget_view_id}/project_status_snapshots/get/responses/422",
          "via": []
        },
        "availability": {
          "status_code": "native",
          "media_type": "native",
          "schema_id": "adapter",
          "description": "native",
          "provenance": "native"
        }
      }
    ]
  },
  "effective": {
    "parameters": [
      {
        "name": "filters[approval_status]",
        "location": "query",
        "required": false,
        "schema_id": "schema:anon/dd14b24ce32314f1bbc082942a125f34821ed7fb",
        "description": "Filter by approval status",
        "deprecated": null,
        "explode": null,
        "style": null,
        "provenance": {
          "source_file": "/Users/taylorhale/Documents/dev_hub/Brynhild/repos/Schmith/spec/procore/api.json",
          "source_pointer": "#/paths//rest/v2.0/companies/{company_id}/budget_views/{budget_view_id}/project_status_snapshots/get/parameters",
          "via": []
        },
        "availability": {
          "name": "native",
          "location": "native",
          "required": "native",
          "schema_id": "adapter",
          "description": "native",
          "deprecated": "absent",
          "explode": "absent",
          "style": "absent",
          "provenance": "native"
        }
      },
      {
        "name": "filters[status_id]",
        "location": "query",
        "required": false,
        "schema_id": "schema:anon/5b1cd5713a375e18bb93e9635b8a2dc5fc2672cf",
        "description": "Filter snapshots by PSS custom status ID",
        "deprecated": null,
        "explode": null,
        "style": null,
        "provenance": {
          "source_file": "/Users/taylorhale/Documents/dev_hub/Brynhild/repos/Schmith/spec/procore/api.json",
          "source_pointer": "#/paths//rest/v2.0/companies/{company_id}/budget_views/{budget_view_id}/project_status_snapshots/get/parameters",
          "via": []
        },
        "availability": {
          "name": "native",
          "location": "native",
          "required": "native",
          "schema_id": "adapter",
          "description": "native",
          "deprecated": "absent",
          "explode": "absent",
          "style": "absent",
          "provenance": "native"
        }
      },
      {
        "name": "filters[project_id]",
        "location": "query",
        "required": false,
        "schema_id": "schema:anon/5b1cd5713a375e18bb93e9635b8a2dc5fc2672cf",
        "description": "Filter snapshots by project ID",
        "deprecated": null,
        "explode": null,
        "style": null,
        "provenance": {
          "source_file": "/Users/taylorhale/Documents/dev_hub/Brynhild/repos/Schmith/spec/procore/api.json",
          "source_pointer": "#/paths//rest/v2.0/companies/{company_id}/budget_views/{budget_view_id}/project_status_snapshots/get/parameters",
          "via": []
        },
        "availability": {
          "name": "native",
          "location": "native",
          "required": "native",
          "schema_id": "adapter",
          "description": "native",
          "deprecated": "absent",
          "explode": "absent",
          "style": "absent",
          "provenance": "native"
        }
      },
      {
        "name": "filters[region_id]",
        "location": "query",
        "required": false,
        "schema_id": "schema:anon/5b1cd5713a375e18bb93e9635b8a2dc5fc2672cf",
        "description": "Filter snapshots by region ID",
        "deprecated": null,
        "explode": null,
        "style": null,
        "provenance": {
          "source_file": "/Users/taylorhale/Documents/dev_hub/Brynhild/repos/Schmith/spec/procore/api.json",
          "source_pointer": "#/paths//rest/v2.0/companies/{company_id}/budget_views/{budget_view_id}/project_status_snapshots/get/parameters",
          "via": []
        },
        "availability": {
          "name": "native",
          "location": "native",
          "required": "native",
          "schema_id": "adapter",
          "description": "native",
          "deprecated": "absent",
          "explode": "absent",
          "style": "absent",
          "provenance": "native"
        }
      },
      {
        "name": "filters[stage_id]",
        "location": "query",
        "required": false,
        "schema_id": "schema:anon/5b1cd5713a375e18bb93e9635b8a2dc5fc2672cf",
        "description": "Filter snapshots by stage ID",
        "deprecated": null,
        "explode": null,
        "style": null,
        "provenance": {
          "source_file": "/Users/taylorhale/Documents/dev_hub/Brynhild/repos/Schmith/spec/procore/api.json",
          "source_pointer": "#/paths//rest/v2.0/companies/{company_id}/budget_views/{budget_view_id}/project_status_snapshots/get/parameters",
          "via": []
        },
        "availability": {
          "name": "native",
          "location": "native",
          "required": "native",
          "schema_id": "adapter",
          "description": "native",
          "deprecated": "absent",
          "explode": "absent",
          "style": "absent",
          "provenance": "native"
        }
      },
      {
        "name": "filters[office_id]",
        "location": "query",
        "required": false,
        "schema_id": "schema:anon/5b1cd5713a375e18bb93e9635b8a2dc5fc2672cf",
        "description": "Filter snapshots by office ID",
        "deprecated": null,
        "explode": null,
        "style": null,
        "provenance": {
          "source_file": "/Users/taylorhale/Documents/dev_hub/Brynhild/repos/Schmith/spec/procore/api.json",
          "source_pointer": "#/paths//rest/v2.0/companies/{company_id}/budget_views/{budget_view_id}/project_status_snapshots/get/parameters",
          "via": []
        },
        "availability": {
          "name": "native",
          "location": "native",
          "required": "native",
          "schema_id": "adapter",
          "description": "native",
          "deprecated": "absent",
          "explode": "absent",
          "style": "absent",
          "provenance": "native"
        }
      },
      {
        "name": "filters[created_by_id]",
        "location": "query",
        "required": false,
        "schema_id": "schema:anon/5b1cd5713a375e18bb93e9635b8a2dc5fc2672cf",
        "description": "Filter snapshots by created_by_id",
        "deprecated": null,
        "explode": null,
        "style": null,
        "provenance": {
          "source_file": "/Users/taylorhale/Documents/dev_hub/Brynhild/repos/Schmith/spec/procore/api.json",
          "source_pointer": "#/paths//rest/v2.0/companies/{company_id}/budget_views/{budget_view_id}/project_status_snapshots/get/parameters",
          "via": []
        },
        "availability": {
          "name": "native",
          "location": "native",
          "required": "native",
          "schema_id": "adapter",
          "description": "native",
          "deprecated": "absent",
          "explode": "absent",
          "style": "absent",
          "provenance": "native"
        }
      },
      {
        "name": "filters[created_at]",
        "location": "query",
        "required": false,
        "schema_id": "schema:anon/896926c1f43693d85bb57bbd5c316c6c06b025b8",
        "description": "Filter snapshots by created_at date range, inclusive",
        "deprecated": null,
        "explode": null,
        "style": null,
        "provenance": {
          "source_file": "/Users/taylorhale/Documents/dev_hub/Brynhild/repos/Schmith/spec/procore/api.json",
          "source_pointer": "#/paths//rest/v2.0/companies/{company_id}/budget_views/{budget_view_id}/project_status_snapshots/get/parameters",
          "via": []
        },
        "availability": {
          "name": "native",
          "location": "native",
          "required": "native",
          "schema_id": "adapter",
          "description": "native",
          "deprecated": "absent",
          "explode": "absent",
          "style": "absent",
          "provenance": "native"
        }
      },
      {
        "name": "sort",
        "location": "query",
        "required": false,
        "schema_id": "schema:anon/cfafced046e509146c9abefe0824cf3dc9beb349",
        "description": "Sort parameter",
        "deprecated": null,
        "explode": null,
        "style": null,
        "provenance": {
          "source_file": "/Users/taylorhale/Documents/dev_hub/Brynhild/repos/Schmith/spec/procore/api.json",
          "source_pointer": "#/paths//rest/v2.0/companies/{company_id}/budget_views/{budget_view_id}/project_status_snapshots/get/parameters",
          "via": []
        },
        "availability": {
          "name": "native",
          "location": "native",
          "required": "native",
          "schema_id": "adapter",
          "description": "native",
          "deprecated": "absent",
          "explode": "absent",
          "style": "absent",
          "provenance": "native"
        }
      },
      {
        "name": "page",
        "location": "query",
        "required": false,
        "schema_id": "schema:anon/4df23f6fcb2f843ba1603f8fd67bfbb0659b678d",
        "description": "Page",
        "deprecated": null,
        "explode": null,
        "style": null,
        "provenance": {
          "source_file": "/Users/taylorhale/Documents/dev_hub/Brynhild/repos/Schmith/spec/procore/api.json",
          "source_pointer": "#/paths//rest/v2.0/companies/{company_id}/budget_views/{budget_view_id}/project_status_snapshots/get/parameters",
          "via": []
        },
        "availability": {
          "name": "native",
          "location": "native",
          "required": "native",
          "schema_id": "adapter",
          "description": "native",
          "deprecated": "absent",
          "explode": "absent",
          "style": "absent",
          "provenance": "native"
        }
      },
      {
        "name": "per_page",
        "location": "query",
        "required": false,
        "schema_id": "schema:anon/88ee9d4fe668231f605731a691290c81b2c96179",
        "description": "Elements per page",
        "deprecated": null,
        "explode": null,
        "style": null,
        "provenance": {
          "source_file": "/Users/taylorhale/Documents/dev_hub/Brynhild/repos/Schmith/spec/procore/api.json",
          "source_pointer": "#/paths//rest/v2.0/companies/{company_id}/budget_views/{budget_view_id}/project_status_snapshots/get/parameters",
          "via": []
        },
        "availability": {
          "name": "native",
          "location": "native",
          "required": "native",
          "schema_id": "adapter",
          "description": "native",
          "deprecated": "absent",
          "explode": "absent",
          "style": "absent",
          "provenance": "native"
        }
      },
      {
        "name": "Procore-Company-Id",
        "location": "header",
        "required": true,
        "schema_id": "schema:anon/4df23f6fcb2f843ba1603f8fd67bfbb0659b678d",
        "description": "Unique company identifier associated with the Procore User Account.",
        "deprecated": null,
        "explode": null,
        "style": null,
        "provenance": {
          "source_file": "/Users/taylorhale/Documents/dev_hub/Brynhild/repos/Schmith/spec/procore/api.json",
          "source_pointer": "#/paths//rest/v2.0/companies/{company_id}/budget_views/{budget_view_id}/project_status_snapshots/get/parameters",
          "via": []
        },
        "availability": {
          "name": "native",
          "location": "native",
          "required": "native",
          "schema_id": "adapter",
          "description": "native",
          "deprecated": "absent",
          "explode": "absent",
          "style": "absent",
          "provenance": "native"
        }
      },
      {
        "name": "company_id",
        "location": "path",
        "required": true,
        "schema_id": "schema:anon/5b1cd5713a375e18bb93e9635b8a2dc5fc2672cf",
        "description": "Unique identifier for the company.",
        "deprecated": null,
        "explode": null,
        "style": null,
        "provenance": {
          "source_file": "/Users/taylorhale/Documents/dev_hub/Brynhild/repos/Schmith/spec/procore/api.json",
          "source_pointer": "#/paths//rest/v2.0/companies/{company_id}/budget_views/{budget_view_id}/project_status_snapshots/get/parameters",
          "via": []
        },
        "availability": {
          "name": "native",
          "location": "native",
          "required": "native",
          "schema_id": "adapter",
          "description": "native",
          "deprecated": "absent",
          "explode": "absent",
          "style": "absent",
          "provenance": "native"
        }
      },
      {
        "name": "budget_view_id",
        "location": "path",
        "required": true,
        "schema_id": "schema:anon/5b1cd5713a375e18bb93e9635b8a2dc5fc2672cf",
        "description": "ID of the budget view",
        "deprecated": null,
        "explode": null,
        "style": null,
        "provenance": {
          "source_file": "/Users/taylorhale/Documents/dev_hub/Brynhild/repos/Schmith/spec/procore/api.json",
          "source_pointer": "#/paths//rest/v2.0/companies/{company_id}/budget_views/{budget_view_id}/project_status_snapshots/get/parameters",
          "via": []
        },
        "availability": {
          "name": "native",
          "location": "native",
          "required": "native",
          "schema_id": "adapter",
          "description": "native",
          "deprecated": "absent",
          "explode": "absent",
          "style": "absent",
          "provenance": "native"
        }
      }
    ],
    "request_bodies": [],
    "responses": [
      {
        "status_code": "200",
        "media_type": "application/json",
        "schema_id": "schema:anon/acd798d584ee5ff3e54e26fc31fb105ca48c0a49",
        "description": "OK",
        "provenance": {
          "source_file": "/Users/taylorhale/Documents/dev_hub/Brynhild/repos/Schmith/spec/procore/api.json",
          "source_pointer": "#/paths//rest/v2.0/companies/{company_id}/budget_views/{budget_view_id}/project_status_snapshots/get/responses/200",
          "via": []
        },
        "availability": {
          "status_code": "native",
          "media_type": "native",
          "schema_id": "adapter",
          "description": "native",
          "provenance": "native"
        }
      },
      {
        "status_code": "400",
        "media_type": "application/json",
        "schema_id": "schema:anon/3ff1c5fdb9b08c6e4d5f4bea9bae42c60eb39a1a",
        "description": "Bad Request",
        "provenance": {
          "source_file": "/Users/taylorhale/Documents/dev_hub/Brynhild/repos/Schmith/spec/procore/api.json",
          "source_pointer": "#/paths//rest/v2.0/companies/{company_id}/budget_views/{budget_view_id}/project_status_snapshots/get/responses/400",
          "via": []
        },
        "availability": {
          "status_code": "native",
          "media_type": "native",
          "schema_id": "adapter",
          "description": "native",
          "provenance": "native"
        }
      },
      {
        "status_code": "401",
        "media_type": "application/json",
        "schema_id": "schema:anon/3ff1c5fdb9b08c6e4d5f4bea9bae42c60eb39a1a",
        "description": "Unauthorized",
        "provenance": {
          "source_file": "/Users/taylorhale/Documents/dev_hub/Brynhild/repos/Schmith/spec/procore/api.json",
          "source_pointer": "#/paths//rest/v2.0/companies/{company_id}/budget_views/{budget_view_id}/project_status_snapshots/get/responses/401",
          "via": []
        },
        "availability": {
          "status_code": "native",
          "media_type": "native",
          "schema_id": "adapter",
          "description": "native",
          "provenance": "native"
        }
      },
      {
        "status_code": "403",
        "media_type": "application/json",
        "schema_id": "schema:anon/3ff1c5fdb9b08c6e4d5f4bea9bae42c60eb39a1a",
        "description": "Forbidden",
        "provenance": {
          "source_file": "/Users/taylorhale/Documents/dev_hub/Brynhild/repos/Schmith/spec/procore/api.json",
          "source_pointer": "#/paths//rest/v2.0/companies/{company_id}/budget_views/{budget_view_id}/project_status_snapshots/get/responses/403",
          "via": []
        },
        "availability": {
          "status_code": "native",
          "media_type": "native",
          "schema_id": "adapter",
          "description": "native",
          "provenance": "native"
        }
      },
      {
        "status_code": "422",
        "media_type": "application/json",
        "schema_id": "schema:anon/3ff1c5fdb9b08c6e4d5f4bea9bae42c60eb39a1a",
        "description": "Unprocessable Entity",
        "provenance": {
          "source_file": "/Users/taylorhale/Documents/dev_hub/Brynhild/repos/Schmith/spec/procore/api.json",
          "source_pointer": "#/paths//rest/v2.0/companies/{company_id}/budget_views/{budget_view_id}/project_status_snapshots/get/responses/422",
          "via": []
        },
        "availability": {
          "status_code": "native",
          "media_type": "native",
          "schema_id": "adapter",
          "description": "native",
          "provenance": "native"
        }
      }
    ]
  },
  "tags": [
    "Construction Financials/Budget/budget-project-status-snapshots"
  ],
  "summary": "List Company Project Status Snapshots",
  "description": "Returns a paginated list of company-level Project Status snapshots with optional filtering and sorting",
  "provenance": {
    "source_file": "/Users/taylorhale/Documents/dev_hub/Brynhild/repos/Schmith/spec/procore/api.json",
    "source_pointer": "#/paths//rest/v2.0/companies/{company_id}/budget_views/{budget_view_id}/project_status_snapshots/get",
    "via": []
  },
  "availability": {
    "id": "adapter",
    "method": "native",
    "path_template": "native",
    "declared": "adapter",
    "effective": "adapter",
    "tags": "native",
    "summary": "native",
    "description": "native"
  }
}
