{
  "id": "schema:anon/056d854d5c9f30f59ae2545d80807cdf29bcaebc",
  "name_hint": null,
  "kind": "object",
  "title": null,
  "description": "Configuration values for an configuration of an app installation.",
  "enum_values": null,
  "enum_names": null,
  "properties": [],
  "required": [],
  "items_schema_id": null,
  "additional_properties_schema_id": null,
  "constraints": {},
  "composition": null,
  "provenance": {
    "source_file": "/Users/taylorhale/Documents/dev_hub/Brynhild/repos/Schmith/spec/procore/api.json",
    "source_pointer": "#/paths//rest/v1.0/companies/{company_id}/app_configurations/{id}/patch/requestBody/content/application/json",
    "via": []
  },
  "is_inline": true,
  "availability": {
    "id": "adapter",
    "name_hint": "absent",
    "kind": "native",
    "title": "absent",
    "description": "native",
    "enum_values": "absent",
    "enum_names": "absent",
    "properties": "absent",
    "required": "absent",
    "items_schema_id": "absent",
    "additional_properties_schema_id": "absent",
    "constraints": "absent",
    "composition": "absent",
    "provenance": "native",
    "where_used": "absent"
  },
  "where_used": []
}
