{
  "id": "schema:definitions/MailMessageBase",
  "name_hint": "MailMessageBase",
  "kind": "unknown",
  "title": null,
  "description": null,
  "enum_values": null,
  "enum_names": null,
  "properties": [
    {
      "json_name": "recipient",
      "schema_id": "schema:definitions/MailRecipient",
      "required": true,
      "nullable": null,
      "description": null,
      "deprecated": null,
      "read_only": null,
      "write_only": null,
      "examples": null,
      "constraints": {},
      "enum_values": null,
      "enum_names": null,
      "json_pointer": "$.recipient",
      "provenance": {
        "source_file": "/Users/taylorhale/Documents/dev_hub/Brynhild/repos/Schmith/spec/ukg_v2_client/api.yml",
        "source_pointer": "#/definitions/MailMessageBase",
        "via": []
      },
      "availability": {
        "json_name": "native",
        "schema_id": "adapter",
        "required": "native",
        "nullable": "absent",
        "description": "absent",
        "deprecated": "absent",
        "read_only": "absent",
        "write_only": "absent",
        "examples": "absent",
        "enum_values": "absent",
        "enum_names": "absent",
        "json_pointer": "adapter",
        "provenance": "native"
      }
    },
    {
      "json_name": "document_url",
      "schema_id": "schema:anon/70344d19740ede84978aa1e3751773a610f03383",
      "required": true,
      "nullable": null,
      "description": "Html url encoded of the document",
      "deprecated": null,
      "read_only": null,
      "write_only": null,
      "examples": null,
      "constraints": {},
      "enum_values": null,
      "enum_names": null,
      "json_pointer": "$.document_url",
      "provenance": {
        "source_file": "/Users/taylorhale/Documents/dev_hub/Brynhild/repos/Schmith/spec/ukg_v2_client/api.yml",
        "source_pointer": "#/definitions/MailMessageBase",
        "via": []
      },
      "availability": {
        "json_name": "native",
        "schema_id": "adapter",
        "required": "native",
        "nullable": "absent",
        "description": "native",
        "deprecated": "absent",
        "read_only": "absent",
        "write_only": "absent",
        "examples": "absent",
        "enum_values": "absent",
        "enum_names": "absent",
        "json_pointer": "adapter",
        "provenance": "native"
      }
    },
    {
      "json_name": "campaign_id",
      "schema_id": "schema:anon/d14b35b5e20dabb915356187fa3cfec24a00a74d",
      "required": true,
      "nullable": null,
      "description": "ID of a previously created email campaign. If this parameter is a valid campaign ID, the email will be added to the campaign and will be sent on campaign commit. If absent or null, the email will be sent independently as soon as possible.",
      "deprecated": null,
      "read_only": null,
      "write_only": null,
      "examples": null,
      "constraints": {},
      "enum_values": null,
      "enum_names": null,
      "json_pointer": "$.campaign_id",
      "provenance": {
        "source_file": "/Users/taylorhale/Documents/dev_hub/Brynhild/repos/Schmith/spec/ukg_v2_client/api.yml",
        "source_pointer": "#/definitions/MailMessageBase",
        "via": []
      },
      "availability": {
        "json_name": "native",
        "schema_id": "adapter",
        "required": "native",
        "nullable": "absent",
        "description": "native",
        "deprecated": "absent",
        "read_only": "absent",
        "write_only": "absent",
        "examples": "absent",
        "enum_values": "absent",
        "enum_names": "absent",
        "json_pointer": "adapter",
        "provenance": "native"
      }
    },
    {
      "json_name": "spool_index",
      "schema_id": "schema:anon/b6de3ef24765bb01c76034786fb0c626192cfcf4",
      "required": true,
      "nullable": null,
      "description": "Index in the spool (must be unique by document for a given campaign)",
      "deprecated": null,
      "read_only": null,
      "write_only": null,
      "examples": null,
      "constraints": {},
      "enum_values": null,
      "enum_names": null,
      "json_pointer": "$.spool_index",
      "provenance": {
        "source_file": "/Users/taylorhale/Documents/dev_hub/Brynhild/repos/Schmith/spec/ukg_v2_client/api.yml",
        "source_pointer": "#/definitions/MailMessageBase",
        "via": []
      },
      "availability": {
        "json_name": "native",
        "schema_id": "adapter",
        "required": "native",
        "nullable": "absent",
        "description": "native",
        "deprecated": "absent",
        "read_only": "absent",
        "write_only": "absent",
        "examples": "absent",
        "enum_values": "absent",
        "enum_names": "absent",
        "json_pointer": "adapter",
        "provenance": "native"
      }
    }
  ],
  "required": [
    "recipient",
    "campaign_id",
    "document_url",
    "spool_index"
  ],
  "items_schema_id": null,
  "additional_properties_schema_id": null,
  "constraints": {},
  "composition": null,
  "provenance": {
    "source_file": "/Users/taylorhale/Documents/dev_hub/Brynhild/repos/Schmith/spec/ukg_v2_client/api.yml",
    "source_pointer": "#/definitions/MailMessageBase",
    "via": []
  },
  "is_inline": false,
  "availability": {
    "id": "adapter",
    "name_hint": "native",
    "kind": "absent",
    "title": "absent",
    "description": "absent",
    "enum_values": "absent",
    "enum_names": "absent",
    "properties": "native",
    "required": "native",
    "items_schema_id": "absent",
    "additional_properties_schema_id": "absent",
    "constraints": "absent",
    "composition": "absent",
    "provenance": "native",
    "where_used": "absent"
  },
  "where_used": []
}
